minisbd/__init__.py
minisbd/inference.py
minisbd/minisbd.py
minisbd/models.py
minisbd/modules/CREDITS.txt
minisbd/modules/LICENSE.txt
minisbd/modules/__init__.py
minisbd/modules/data.py
minisbd/modules/dictionary.py
minisbd/modules/inference.py
minisbd/modules/vocab.py
minisbd-0.9.1.dist-info/METADATA
minisbd-0.9.1.dist-info/WHEEL
minisbd-0.9.1.dist-info/licenses/LICENSE
minisbd-0.9.1.dist-info/RECORD
