Metadata-Version: 2.4
Name: minisbd
Version: 0.9.1
Summary: Free and open source library for fast sentence boundary detection
Project-URL: Homepage, https://github.com/LibreTranslate/MiniSBD
Project-URL: Source, https://github.com/LibreTranslate/MiniSBD
Project-URL: Documentation, https://github.com/LibreTranslate/MiniSBD
Project-URL: Tracker, https://github.com/LibreTranslate/MiniSBD/issues
Project-URL: History, https://github.com/LibreTranslate/MiniSBD/releases
Author: LibreTranslate Authors
Author-email: Piero Toffanin <pt@masseranolabs.com>
Maintainer: LibreTranslate Authors
Maintainer-email: Piero Toffanin <pt@masseranolabs.com>
License:                     GNU AFFERO GENERAL PUBLIC LICENSE
License-File: LICENSE
Keywords: Python,sbd,sentence-boundary-detection
Classifier: License :: OSI Approved :: GNU Affero General Public License v3
Classifier: Operating System :: OS Independent
Classifier: Programming Language :: Python :: 3
Classifier: Programming Language :: Python :: 3.6
Classifier: Programming Language :: Python :: 3.7
Classifier: Programming Language :: Python :: 3.8
Classifier: Programming Language :: Python :: 3.9
Classifier: Programming Language :: Python :: 3.10
Classifier: Programming Language :: Python :: 3.11
Classifier: Programming Language :: Python :: 3.12
Classifier: Programming Language :: Python :: 3.13
Requires-Python: >=3.6
Requires-Dist: numpy>=1.19.5
Requires-Dist: onnxruntime>=1.10.0
Provides-Extra: dev
Requires-Dist: onnx>=1.20.0; extra == 'dev'
Requires-Dist: onnxsim-prebuilt>=0.4.36.post1; extra == 'dev'
Requires-Dist: stanza==1.10.1; extra == 'dev'
Requires-Dist: wikipedia-api>=0.8.1; extra == 'dev'
Provides-Extra: test
Requires-Dist: pytest>=7.2.0; extra == 'test'
